rutabaga/__init__.py
rutabaga-0.0.2.dist-info/DESCRIPTION.rst
rutabaga-0.0.2.dist-info/METADATA
rutabaga-0.0.2.dist-info/RECORD
rutabaga-0.0.2.dist-info/WHEEL
rutabaga-0.0.2.dist-info/metadata.json
rutabaga-0.0.2.dist-info/namespace_packages.txt
rutabaga-0.0.2.dist-info/top_level.txt
rutabaga-0.0.2.dist-info/zip-safe
